{"base_url":"","routes":{"api_get_department_users":{"tokens":[["text","\/users"],["variable","\/","[^\/]++","id",true],["text","\/api\/department"]],"defaults":[],"requirements":[],"hosttokens":[],"methods":["GET"],"schemes":[]},"event_approve":{"tokens":[["text","\/approve"],["variable","\/","[^\/]++","event",true],["text","\/event"],["variable","\/","[^\/]++","_locale",true]],"defaults":{"event":null,"_locale":""},"requirements":[],"hosttokens":[],"methods":["GET"],"schemes":[]},"event_deny":{"tokens":[["text","\/deny"],["variable","\/","[^\/]++","event",true],["text","\/event"],["variable","\/","[^\/]++","_locale",true]],"defaults":{"event":null,"_locale":""},"requirements":[],"hosttokens":[],"methods":["GET"],"schemes":[]},"event_edit":{"tokens":[["text","\/edit"],["variable","\/","[^\/]++","event",true],["text","\/event"],["variable","\/","[^\/]++","_locale",true]],"defaults":{"_locale":""},"requirements":[],"hosttokens":[],"methods":["GET"],"schemes":[]},"event_delete":{"tokens":[["text","\/delete"],["variable","\/","[^\/]++","event",true],["text","\/event"],["variable","\/","[^\/]++","_locale",true]],"defaults":{"event":null,"_locale":""},"requirements":[],"hosttokens":[],"methods":["GET"],"schemes":[]},"bazinga_jstranslation_js":{"tokens":[["variable",".","js|json","_format",true],["variable","\/","[\\w]+","domain",true],["text","\/translations"]],"defaults":{"domain":"messages","_format":"js"},"requirements":{"_format":"js|json","domain":"[\\w]+"},"hosttokens":[],"methods":["GET"],"schemes":[]}},"prefix":"","host":"localhost","port":"","scheme":"http","locale":""}